privat24_business/__init__.py
privat24_business_python_sdk-0.0.1.dist-info/LICENSE
privat24_business_python_sdk-0.0.1.dist-info/METADATA
privat24_business_python_sdk-0.0.1.dist-info/WHEEL
privat24_business_python_sdk-0.0.1.dist-info/top_level.txt
privat24_business_python_sdk-0.0.1.dist-info/RECORD
